{
	"name": "AzureBlobStorage1",
	"properties": {
		"annotations": [],
		"type": "AzureBlobStorage",
		"typeProperties": {
			"serviceEndpoint": "https://devenvstorageacc.blob.core.windows.net/",
			"tenant": "83d3ebc1-48f0-435e-9b65-586a8310af3b",
			"servicePrincipalId": "3589db5a-14ee-4c77-ab0f-0304436ae7b0",
			"servicePrincipalCredentialType": "ServicePrincipalKey",
			"servicePrincipalCredential": {
				"type": "AzureKeyVaultSecret",
				"store": {
					"referenceName": "Mydevkeyvault",
					"type": "LinkedServiceReference"
				},
				"secretName": "SECRETNAME"
			},
			"accountKind": "StorageV2"
		}
	},
	"type": "Microsoft.DataFactory/factories/linkedservices"
}